mempw/__init__.py
mempw/config.py
mempw/core.py
mempw/wordlist.py
mempw-0.1.6.dist-info/LICENCE
mempw-0.1.6.dist-info/METADATA
mempw-0.1.6.dist-info/WHEEL
mempw-0.1.6.dist-info/entry_points.txt
mempw-0.1.6.dist-info/top_level.txt
mempw-0.1.6.dist-info/RECORD
